django_mirror/__init__.py
django_mirror/__version__.py
django_mirror/admin.py
django_mirror/config.py
django_mirror/media.json
django_mirror/media.py
django_mirror/widgets.py
django_mirror/static/django-mirror/admin.css
django_mirror/static/django-mirror/admin.js
django_mirror/static/django-mirror/init.js
django_mirror/static/django-mirror/codemirror/addon/comment/comment.js
django_mirror/static/django-mirror/codemirror/addon/comment/continuecomment.js
django_mirror/static/django-mirror/codemirror/addon/dialog/dialog.css
django_mirror/static/django-mirror/codemirror/addon/dialog/dialog.js
django_mirror/static/django-mirror/codemirror/addon/display/autorefresh.js
django_mirror/static/django-mirror/codemirror/addon/display/fullscreen.css
django_mirror/static/django-mirror/codemirror/addon/display/fullscreen.js
django_mirror/static/django-mirror/codemirror/addon/display/panel.js
django_mirror/static/django-mirror/codemirror/addon/display/placeholder.js
django_mirror/static/django-mirror/codemirror/addon/display/rulers.js
django_mirror/static/django-mirror/codemirror/addon/edit/closebrackets.js
django_mirror/static/django-mirror/codemirror/addon/edit/closetag.js
django_mirror/static/django-mirror/codemirror/addon/edit/continuelist.js
django_mirror/static/django-mirror/codemirror/addon/edit/matchbrackets.js
django_mirror/static/django-mirror/codemirror/addon/edit/matchtags.js
django_mirror/static/django-mirror/codemirror/addon/edit/trailingspace.js
django_mirror/static/django-mirror/codemirror/addon/fold/brace-fold.js
django_mirror/static/django-mirror/codemirror/addon/fold/comment-fold.js
django_mirror/static/django-mirror/codemirror/addon/fold/foldcode.js
django_mirror/static/django-mirror/codemirror/addon/fold/foldgutter.css
django_mirror/static/django-mirror/codemirror/addon/fold/foldgutter.js
django_mirror/static/django-mirror/codemirror/addon/fold/indent-fold.js
django_mirror/static/django-mirror/codemirror/addon/fold/markdown-fold.js
django_mirror-0.1.13.dist-info/COPYING
django_mirror-0.1.13.dist-info/COPYING.LESSER
django_mirror-0.1.13.dist-info/METADATA
django_mirror-0.1.13.dist-info/WHEEL
django_mirror-0.1.13.dist-info/top_level.txt
django_mirror-0.1.13.dist-info/RECORD
