Metadata-Version: 2.1
Name: django-mirror
Version: 0.1.13
Summary: This package marries Django with CodeMirror
Home-page: https://github.com/pavelsof/django-mirror
Author: pavelsof
Author-email: mail@pavelsof.com
License: UNKNOWN
Project-URL: Changelog, https://github.com/pavelsof/django-mirror/blob/master/CHANGELOG.rst
Project-URL: Source, https://github.com/pavelsof/django-mirror
Project-URL: Tracker, https://github.com/pavelsof/django-mirror/issues
Keywords: django codemirror
Platform: UNKNOWN
Classifier: Development Status :: 4 - Beta
Classifier: Environment :: Web Environment
Classifier: Framework :: Django
Classifier: Intended Audience :: Developers
Classifier: License :: OSI Approved :: GNU Lesser General Public License v3 (LGPLv3)
Classifier: Programming Language :: Python :: 3
Classifier: Topic :: Internet :: WWW/HTTP
Requires-Python: >=3
Requires-Dist: django (>=2.2)
